README.md
setup.py
appscale/agents/__init__.py
appscale/agents/agent_exceptions.py
appscale/agents/azure_agent.py
appscale/agents/base_agent.py
appscale/agents/config.py
appscale/agents/ec2_agent.py
appscale/agents/euca_agent.py
appscale/agents/factory.py
appscale/agents/gce_agent.py
appscale/agents/openstack_agent.py
appscale_agents.egg-info/PKG-INFO
appscale_agents.egg-info/SOURCES.txt
appscale_agents.egg-info/dependency_links.txt
appscale_agents.egg-info/entry_points.txt
appscale_agents.egg-info/namespace_packages.txt
appscale_agents.egg-info/requires.txt
appscale_agents.egg-info/top_level.txt
test/test_agent_ec2.py
test/test_agent_euca.py
test/test_agent_factory.py
test/test_agent_gce.py
test/test_base_agent.py
test/test_config_appscale_state.py